ssam_ew/__init__.py
ssam_ew/magma.py
ssam_ew/ssam.py
ssam_ew-1.1.5.dist-info/LICENSE
ssam_ew-1.1.5.dist-info/WHEEL
ssam_ew-1.1.5.dist-info/METADATA
ssam_ew-1.1.5.dist-info/RECORD
